shapefinder/__init__.py
shapefinder/shape.py
shapefinder/__pycache__/__init__.cpython-38.pyc
shapefinder/__pycache__/shape.cpython-38.pyc
shapefinder-0.1.0.dist-info/LICENSE
shapefinder-0.1.0.dist-info/METADATA
shapefinder-0.1.0.dist-info/WHEEL
shapefinder-0.1.0.dist-info/top_level.txt
shapefinder-0.1.0.dist-info/RECORD
