Metadata-Version: 2.1
Name: shapefinder
Version: 0.1.0
Summary: A tool to find patterns in time series dataset and forecast
Author-email: Thomas Schincariol <thomas.schincariol@gmail.com>
License: MIT
Project-URL: Homepage, https://github.com/ThomasSchinca/shapefinder
Project-URL: Issues, https://github.com/ThomasSchinca/shapefinder/issues
Keywords: python,time series,find,pattern
Requires-Python: >=3.8
License-File: LICENSE
Requires-Dist: pandas (==1.1.5)
Requires-Dist: matplotlib (==3.3.4)
Requires-Dist: numpy (==1.19.5)
Requires-Dist: scipy (==1.5.4)
Requires-Dist: dtaidistance (==2.3.10)
Requires-Dist: plotly (==4.14.3)
Requires-Dist: POT (==0.7.0)
